{
  "pop": 8,
  "elitism": 2,
  "gen_per_week": 1,
  "shadow_days": 14,
  "live_gate": {"WR":0.55,"PF":1.20,"DD_day":0.03,"Cost_bps":25,"CorrMax":0.75},
  "param_space": {
    "FVG_MIN_PCT": [3,4,5,6,7],
    "TF": ["1h","4h"],
    "HALF": ["on","off"],
    "ORB_WIN": [15,30,60],
    "RSI_LEN": [7,14],
    "MACD_FAST": [9,12],
    "MACD_SLOW": [26],
    "VWAP_BAND": [0.5,1.0]
  },
  "blocks_pool": {
    "entry": ["FVG_IN","ORB","MACD_RSI"],
    "filter": ["VWAP","SR"],
    "exit": ["SUPERTR","RSI_EXIT","TIMESTOP"],
    "risk": ["ATR_SL","HALF_TP","TRAIL"]
  },
  "block_max": 6
}